EMpy/RCWA.py
EMpy/__init__.py
EMpy/_version.py
EMpy/constants.py
EMpy/devices.py
EMpy/materials.py
EMpy/scattering.py
EMpy/transfer_matrix.py
EMpy/utils.py
EMpy/modesolvers/FD.py
EMpy/modesolvers/FMM.py
EMpy/modesolvers/__init__.py
EMpy/modesolvers/geometries.py
EMpy/modesolvers/interface.py
electromagneticpython-2.2.3.dist-info/licenses/LICENSE
examples/ex_APRR.py
examples/ex_NRR.py
examples/ex_RCWA.py
examples/ex_RCWA_2.py
examples/ex_RCWA_3.py
examples/ex_SRR.py
examples/ex_laser_etch_monitor.py
examples/ex_modesolver.py
examples/ex_modesolver_2.py
examples/ex_modesolver_3.py
examples/ex_modesolver_4.py
examples/ex_modesolver_dch.py
examples/ex_modesolver_dch_anis.py
examples/ex_transfer_matrix.py
examples/ex_transfer_matrix_2.py
examples/ex_transfer_matrix_2.py.png
examples/ex_transfer_matrix_3.py
examples/lc_data.dat
examples/nk.py
scripts/FDTD.py
tests/__init__.py
tests/devices_test.py
tests/materials_test.py
tests/modesolvers_test.py
tests/utils_test.py
electromagneticpython-2.2.3.dist-info/METADATA
electromagneticpython-2.2.3.dist-info/WHEEL
electromagneticpython-2.2.3.dist-info/top_level.txt
electromagneticpython-2.2.3.dist-info/RECORD
