Metadata-Version: 2.4
Name: ElectroMagneticPython
Version: 2.2.3
Summary: EMpy - ElectroMagnetic Python
Author-email: Lorenzo Bolla <code@lbolla.info>
License-Expression: MIT
Project-URL: Homepage, http://lbolla.github.io/EMpy/
Project-URL: Repository, https://github.com/lbolla/EMpy
Classifier: Development Status :: 5 - Production/Stable
Classifier: Environment :: Console
Classifier: Intended Audience :: Science/Research
Classifier: Natural Language :: English
Classifier: Programming Language :: Python :: 3
Classifier: Operating System :: OS Independent
Classifier: Topic :: Scientific/Engineering :: Physics
Requires-Python: >=3.10
License-File: LICENSE
Requires-Dist: numpy>=1.18
Requires-Dist: scipy>=1.7
Requires-Dist: matplotlib>=3.1
Dynamic: license-file
